streamlit_supabase_auth_ui/__init__.py
streamlit_supabase_auth_ui/secretsStreamlit.py
streamlit_supabase_auth_ui/utils.py
streamlit_supabase_auth_ui/widgets.py
streamlit_supabase_auth_ui-0.2.0.dist-info/METADATA
streamlit_supabase_auth_ui-0.2.0.dist-info/WHEEL
streamlit_supabase_auth_ui-0.2.0.dist-info/top_level.txt
streamlit_supabase_auth_ui-0.2.0.dist-info/RECORD
