Metadata-Version: 2.4
Name: streamlit-supabase-auth-ui
Version: 0.2.0
Summary: Seamless Supabase authentication for seamless Streamlit apps
Author-email: Clelia Astra Bertelli <astraberte9@gmail.com>
Project-URL: Homepage, https://github.com/AstraBert/streamlit_supabase_auth_ui
Project-URL: Issues, https://github.com/AstraBert/streamlit_supabase_auth_ui/issues
Classifier: Programming Language :: Python :: 3
Classifier: License :: OSI Approved :: MIT License
Classifier: Operating System :: OS Independent
Requires-Python: >=3.10
Requires-Dist: requests==2.32.3
Requires-Dist: streamlit==1.39.0
Requires-Dist: streamlit-cookies-manager==0.2.0
Requires-Dist: streamlit-lottie==0.0.5
Requires-Dist: streamlit-option-menu==0.4.0
Requires-Dist: supabase==2.9.1
Requires-Dist: trycourier==6.2.0
